hack_vm_translator_brickman/__init__.py
hack_vm_translator_brickman/atomic_commands.py
hack_vm_translator_brickman/translator.py
hack_vm_translator_brickman/virtual_commands.py
hack_vm_translator_brickman-0.0.3.dist-info/LICENSE.txt
hack_vm_translator_brickman-0.0.3.dist-info/METADATA
hack_vm_translator_brickman-0.0.3.dist-info/WHEEL
hack_vm_translator_brickman-0.0.3.dist-info/top_level.txt
hack_vm_translator_brickman-0.0.3.dist-info/RECORD
